Metadata-Version: 1.0
Name: calculator-metatron
Version: 1.0.0
Summary: Simple calculator with python
Home-page: UNKNOWN
Author: Rômulo do Carmo Sousa
Author-email: romulocarmos@gmail.com
License: MIT
Platform: UNKNOWN
